pygubernator/__init__.py
pygubernator/py.typed
pygubernator/actions/__init__.py
pygubernator/actions/executor.py
pygubernator/actions/registry.py
pygubernator/config/__init__.py
pygubernator/config/loader.py
pygubernator/config/validator.py
pygubernator/config/schemas/machine.json
pygubernator/core/__init__.py
pygubernator/core/errors.py
pygubernator/core/event.py
pygubernator/core/machine.py
pygubernator/core/state.py
pygubernator/core/transition.py
pygubernator/guards/__init__.py
pygubernator/guards/builtins.py
pygubernator/guards/evaluator.py
pygubernator/guards/registry.py
pygubernator/timeout/__init__.py
pygubernator/timeout/manager.py
pygubernator/utils/__init__.py
pygubernator/utils/serialization.py
pygubernator-0.0.1.dist-info/licenses/LICENSE
pygubernator-0.0.1.dist-info/METADATA
pygubernator-0.0.1.dist-info/WHEEL
pygubernator-0.0.1.dist-info/top_level.txt
pygubernator-0.0.1.dist-info/RECORD
