Metadata-Version: 2.4
Name: pygubernator
Version: 0.0.1
Summary: A configuration-driven, stateless finite state machine library for Python
Author-email: StatFYI <contact@statfyi.com>
License: MIT
Project-URL: Homepage, https://github.com/statfyi/pygubernator
Project-URL: Documentation, https://github.com/statfyi/pygubernator#readme
Project-URL: Repository, https://github.com/statfyi/pygubernator
Project-URL: Issues, https://github.com/statfyi/pygubernator/issues
Project-URL: Changelog, https://github.com/statfyi/pygubernator/blob/main/CHANGELOG.md
Keywords: state-machine,fsm,finite-state-machine,workflow,configuration-driven,declarative,guards,transitions,order-management,event-driven
Classifier: Development Status :: 4 - Beta
Classifier: Intended Audience :: Developers
Classifier: License :: OSI Approved :: MIT License
Classifier: Operating System :: OS Independent
Classifier: Programming Language :: Python :: 3
Classifier: Programming Language :: Python :: 3.10
Classifier: Programming Language :: Python :: 3.11
Classifier: Programming Language :: Python :: 3.12
Classifier: Programming Language :: Python :: 3.13
Classifier: Typing :: Typed
Classifier: Topic :: Software Development :: Libraries :: Python Modules
Classifier: Topic :: Software Development :: Libraries :: Application Frameworks
Requires-Python: >=3.10
License-File: LICENSE
Requires-Dist: pyyaml>=6.0
Requires-Dist: jsonschema>=4.20.0
Provides-Extra: dev
Requires-Dist: pytest>=7.4.0; extra == "dev"
Requires-Dist: pytest-cov>=4.1.0; extra == "dev"
Requires-Dist: ruff>=0.4.0; extra == "dev"
Requires-Dist: mypy>=1.8.0; extra == "dev"
Requires-Dist: build>=1.0.0; extra == "dev"
Requires-Dist: twine>=5.0.0; extra == "dev"
Requires-Dist: types-PyYAML>=6.0.0; extra == "dev"
Dynamic: license-file
